<annotation>
	<folder>xml</folder>
	<filename>截屏2024-01-01 17.09.18.png</filename>
	<path>/Users/liuquan/Desktop/VscodeProject/ github code/YOLOX_Gauss/gaosi/xml/截屏2024-01-01 17.09.18.png</path>
	<source>
		<database>Unknown</database>
	</source>
	<size>
		<width>1618</width>
		<height>908</height>
		<depth>3</depth>
	</size>
	<segmented>0</segmented>
	<object>
		<name>pentagon</name>
		<pose>Unspecified</pose>
		<truncated>0</truncated>
		<difficult>0</difficult>
		<bndbox>
			<xmin>67</xmin>
			<ymin>115</ymin>
			<xmax>408</xmax>
			<ymax>325</ymax>
		</bndbox>
	</object>
	<object>
		<name>trapezium</name>
		<pose>Unspecified</pose>
		<truncated>0</truncated>
		<difficult>0</difficult>
		<bndbox>
			<xmin>636</xmin>
			<ymin>137</ymin>
			<xmax>901</xmax>
			<ymax>396</ymax>
		</bndbox>
	</object>
	<object>
		<name>parallelogram</name>
		<pose>Unspecified</pose>
		<truncated>0</truncated>
		<difficult>0</difficult>
		<bndbox>
			<xmin>1155</xmin>
			<ymin>157</ymin>
			<xmax>1439</xmax>
			<ymax>532</ymax>
		</bndbox>
	</object>
	<object>
		<name>triangle</name>
		<pose>Unspecified</pose>
		<truncated>0</truncated>
		<difficult>0</difficult>
		<bndbox>
			<xmin>671</xmin>
			<ymin>388</ymin>
			<xmax>1148</xmax>
			<ymax>710</ymax>
		</bndbox>
	</object>
	<object>
		<name>circle</name>
		<pose>Unspecified</pose>
		<truncated>0</truncated>
		<difficult>0</difficult>
		<bndbox>
			<xmin>88</xmin>
			<ymin>637</ymin>
			<xmax>489</xmax>
			<ymax>847</ymax>
		</bndbox>
	</object>
</annotation>
